 calmecac-tools/__init__.py
 calmecac-tools/hello_module.py
 calmecac_tools/__init__.py
 calmecac_tools/hello_module.py
calmecac_tools/__init__.py
calmecac_tools/hello_module.py
calmecac_tools/tests/__init__.py
calmecac_tools/tests/test_hello_module.py
calmecac_tools-0.0.3.dist-info/METADATA
calmecac_tools-0.0.3.dist-info/WHEEL
calmecac_tools-0.0.3.dist-info/top_level.txt
calmecac_tools-0.0.3.dist-info/RECORD
